human_brain_atlases/__init__.py
human_brain_atlases/atlases/__init__.py
human_brain_atlases/atlases/base.py
human_brain_atlases/atlases/brainnetome.py
human_brain_atlases/atlases/power.py
human_brain_atlases/atlases/schaefer.py
human_brain_atlases/data/__init__.py
human_brain_atlases/data/jonathan_power_2011/Neuron_consensus_264.xlsx
human_brain_atlases/data/jonathan_power_2011/__init__.py
human_brain_atlases/data/jonathan_power_2011/atlas.csv
human_brain_atlases/data/jonathan_power_2011/~$Neuron_consensus_264.xlsx
human_brain_atlases/templates/__init__.py
human_brain_atlases/templates/mni152.py
human_brain_atlases/utils/__init__.py
human_brain_atlases/utils/helpers.py
human_brain_atlases-0.1.6.dist-info/licenses/LICENSE
human_brain_atlases-0.1.6.dist-info/METADATA
human_brain_atlases-0.1.6.dist-info/WHEEL
human_brain_atlases-0.1.6.dist-info/top_level.txt
human_brain_atlases-0.1.6.dist-info/RECORD
